[{"spec":"url","value":"https://www.91-img.com/gallery_images_uploads/b/4/b4e86c766a7500ebfc69821fdc98ad2c501c22ac.jpg?w=0&h=901&q=80&c=1"},{"spec":"RAM","value":"12 GB"},{"spec":"Processor","value":"Qualcomm Snapdragon 888 Plus"},{"spec":"Rear Camera","value":"64 MP + 13 MP + 5 MP"},{"spec":"Front Camera","value":"24 MP"},{"spec":"Battery","value":"6000 mAh"},{"spec":"Display","value":"6.78 inches (17.22 cm)"},{"spec":"Launch Date","value":"February 18, 2022 (Official)"},{"spec":"Operating System","value":"Android v11"},{"spec":"Custom UI","value":"ROG UI"},{"spec":"Chipset","value":"Qualcomm Snapdragon 888 Plus"},{"spec":"CPU","value":"Octa core (3 GHz, Single core, Kryo 680 + 2.42 GHz, Tri core, Kryo 680 + 1.8 GHz, Quad core, Kryo 680)"},{"spec":"Architecture","value":"64 bit"},{"spec":"Fabrication","value":"5 nm"},{"spec":"Graphics","value":"Adreno 660"},{"spec":"RAM","value":"12 GB\nBest in Class ▾"},{"spec":"RAM Type","value":"LPDDR5"},{"spec":"Display Type","value":"AMOLED"},{"spec":"Screen Size","value":"6.78 inches (17.22 cm)"},{"spec":"Resolution","value":"1080 x 2448 pixels"},{"spec":"Aspect Ratio","value":"20:4:9"},{"spec":"Pixel Density","value":"395 ppi\nBest in Class ▾"},{"spec":"Screen to Body Ratio (calculated)","value":"82.07 %"},{"spec":"Screen Protection","value":"Corning Gorilla Glass, Glass Victus"},{"spec":"Bezel-less display","value":"Yes"},{"spec":"Touch Screen","value":"Yes, Capacitive Touchscreen, Multi-touch"},{"spec":"Brightness","value":"1200 nits"},{"spec":"HDR 10 / HDR+ support","value":"Yes, HDR 10+"},{"spec":"Refresh Rate","value":"144 Hz"},{"spec":"Height","value":"173 mm Compare Size"},{"spec":"Width","value":"77 mm"},{"spec":"Thickness","value":"9.9 mm\nAverage ▾"},{"spec":"Weight","value":"238 grams\nPoor ▾"},{"spec":"Colours","value":"Phantom Black, Storm White"},{"spec":"Camera Setup","value":"Triple"},{"spec":"Resolution","value":"64 MP f/1.8, Wide Angle, Primary Camera\n(26 mm focal length, 1.7\" sensor size, 0.8µm pixel size)\n13 MP f/2.4, Ultra-Wide Angle Camera\n(11 mm focal length)\n5 MP f/2.0, Macro Camera"},{"spec":"Sensor","value":"Exmor-RS CMOS Sensor"},{"spec":"Autofocus","value":"Yes, Phase Detection autofocus"},{"spec":"Flash","value":"Yes, LED Flash"},{"spec":"Image Resolution","value":"9000 x 7000 Pixels"},{"spec":"Settings","value":"Exposure compensation, ISO control"},{"spec":"Shooting Modes","value":"Continuous Shooting\nHigh Dynamic Range mode (HDR)"},{"spec":"Camera Features","value":"Digital Zoom\nAuto Flash\nFace detection\nTouch to focus"},{"spec":"Video Recording","value":"7680x4320 @ 30 fps\n3840x2160 @ 60 fps\n1920x1080 @ 240 fps"},{"spec":"Camera Setup","value":"Single"},{"spec":"Resolution","value":"24 MP f/2.0, Wide Angle, Primary Camera\n(27 mm focal length, 0.9µm pixel size)"},{"spec":"Video Recording","value":"1920x1080 @ 30 fps"},{"spec":"Capacity","value":"6000 mAh"},{"spec":"Type","value":"Li-Polymer"},{"spec":"Removable","value":"No"},{"spec":"Quick Charging","value":"Yes, Fast, 65W: 70 % in 30 minutes"},{"spec":"USB Type-C","value":"Yes"},{"spec":"Internal Memory","value":"256 GB\nBest in Class ▾"},{"spec":"Expandable Memory","value":"No"},{"spec":"USB OTG","value":"Yes"},{"spec":"Storage Type","value":"UFS 3.1"},{"spec":"SIM Slot(s)","value":"Dual SIM, GSM+GSM"},{"spec":"SIM Size","value":"SIM1: Nano, SIM2: Nano"},{"spec":"Network Support","value":"5G Supported in India, 4G Supported in India, 3G, 2G"},{"spec":"VoLTE","value":"Yes"},{"spec":"SIM 1","value":"5G Bands:\nFDD N1 / N2 / N3 / N5 / N7 / N8 / N20 / N25 / N28 / N66\nTDD N38 / N40 / N41 / N71 / N77 / N78 / N79\n4G Bands:\nTD-LTE 2600(band 38) / 2300(band 40) / 2500(band 41) / 2100(band 34) / 1900(band 39)\nFD-LTE 2100(band 1) / 1800(band 3) / 2600(band 7) / 900(band 8) / 700(band 28) / 1900(band 2) / 1700(band 4) / 850(band 5) / 700(band 13) / 700(band 17) / 850(band 18) / 850(band 19) / 800(band 20) / 1900(band 25) / 850(band 26) / 700(band 29) / 2300(band 30)\n3G Bands:\nUMTS 1900 / 2100 / 850 / 900 MHz\n2G Bands:\nGSM 1800 / 1900 / 850 / 900 MHz\n\nGPRS:\nAvailable\nEDGE:\nAvailable"},{"spec":"SIM 2","value":"5G Bands:\nFDD N1 / N2 / N3 / N5 / N7 / N8 / N12 / N20 / N25 / N28 / N66\nTDD N38 / N40 / N41 / N71 / N77 / N78 / N79\n4G Bands:\nTD-LTE 2600(band 38) / 2300(band 40) / 2500(band 41) / 2100(band 34) / 1900(band 39)\nFD-LTE 2100(band 1) / 1800(band 3) / 2600(band 7) / 900(band 8) / 700(band 28) / 1900(band 2) / 1700(band 4) / 850(band 5) / 700(band 13) / 700(band 17) / 850(band 18) / 850(band 19) / 800(band 20) / 1900(band 25) / 850(band 26)\n3G Bands:\nUMTS 1900 / 2100 / 850 / 900 MHz\n2G Bands:\nGSM 1800 / 1900 / 850 / 900 MHz\n\nGPRS:\nAvailable\nEDGE:\nAvailable"},{"spec":"SAR Value","value":"Head: 1.180 W/kg"},{"spec":"Wi-Fi","value":"Yes, Wi-Fi 6 (802.11 a/b/g/n/ac/ax) 5GHz, MIMO"},{"spec":"Wi-Fi Features","value":"Wi-Fi Direct, Mobile Hotspot"},{"spec":"Bluetooth","value":"Yes, v5.2"},{"spec":"GPS","value":"Yes with A-GPS, Glonass"},{"spec":"NFC","value":"Yes"},{"spec":"USB Connectivity","value":"Mass storage device, USB charging"},{"spec":"FM Radio","value":"No"},{"spec":"Loudspeaker","value":"Yes"},{"spec":"Audio Jack","value":"3.5 mm"},{"spec":"Fingerprint Sensor","value":"Yes"},{"spec":"Fingerprint Sensor Position","value":"On-screen"},{"spec":"Fingerprint Sensor Type","value":"Optical"},{"spec":"Other Sensors","value":"Light sensor, Proximity sensor, Accelerometer, Compass, Gyroscope"}]